{
  "network": {
    "company": [
      "Comunicare S.r.l."
    ], 
    "href": "/v2/networks/treviso", 
    "id": "treviso", 
    "location": {
      "city": "Treviso", 
      "country": "IT", 
      "latitude": 45.6669011, 
      "longitude": 12.243039
    }, 
    "name": "Treviso", 
    "stations": [
      {
        "empty_slots": 8, 
        "extra": {
          "description": "Via Castello d'Amore", 
          "status": "online"
        }, 
        "free_bikes": 12, 
        "id": "f99334cdea614b26d40f69650b2fcc77", 
        "latitude": 45.67176836862323, 
        "longitude": 12.257416657043109, 
        "name": "Stadio Foro Boario", 
        "timestamp": "2017-08-15T04:46:30.331000Z"
      }, 
      {
        "empty_slots": 5, 
        "extra": {
          "description": "Via Roma", 
          "status": "online"
        }, 
        "free_bikes": 7, 
        "id": "d81b0eb23b438ca4e758b1339c97f85a", 
        "latitude": 45.66105114262774, 
        "longitude": 12.245800750926264, 
        "name": "Stazione FF.SS.", 
        "timestamp": "2017-08-15T04:46:30.353000Z"
      }, 
      {
        "empty_slots": 6, 
        "extra": {
          "description": "Park Dal Negro via Venier", 
          "status": "online"
        }, 
        "free_bikes": 2, 
        "id": "c3614c2cec786f20dbe5bedb75bdeb7f", 
        "latitude": 45.66202582254459, 
        "longitude": 12.252510462210012, 
        "name": "Dal Negro", 
        "timestamp": "2017-08-15T04:46:30.354000Z"
      }, 
      {
        "empty_slots": 7, 
        "extra": {
          "description": "Park Miani viale Orleans", 
          "status": "online"
        }, 
        "free_bikes": 0, 
        "id": "8881a83b96c4e8dc2da3c0ad31e3ee77", 
        "latitude": 45.66351852889419, 
        "longitude": 12.22903762244573, 
        "name": "Miani", 
        "timestamp": "2017-08-15T04:46:30.355000Z"
      }, 
      {
        "empty_slots": 9, 
        "extra": {
          "description": "Piazza Duomo", 
          "status": "online"
        }, 
        "free_bikes": 0, 
        "id": "34a99e1fb50f733ef4ae959d08a60bb3", 
        "latitude": 45.66610056453022, 
        "longitude": 12.24183928605271, 
        "name": "Duomo", 
        "timestamp": "2017-08-15T04:46:30.355000Z"
      }, 
      {
        "empty_slots": 4, 
        "extra": {
          "description": "Piazza Silvio Trentin", 
          "status": "online"
        }, 
        "free_bikes": 4, 
        "id": "823b2ecfd0953a3d0b116fe8ef348034", 
        "latitude": 45.6695674, 
        "longitude": 12.2414515, 
        "name": "Trentin", 
        "timestamp": "2017-08-15T04:46:30.356000Z"
      }, 
      {
        "empty_slots": 5, 
        "extra": {
          "description": "Osp. Ca` Foncello", 
          "status": "online"
        }, 
        "free_bikes": 4, 
        "id": "4779aac4f21615252e65ce8b8b8abd0e", 
        "latitude": 45.659455949334195, 
        "longitude": 12.25941773474051, 
        "name": "Ca` Foncello", 
        "timestamp": "2017-08-15T04:46:30.357000Z"
      }, 
      {
        "empty_slots": 7, 
        "extra": {
          "description": "Piazza Borsa", 
          "status": "online"
        }, 
        "free_bikes": 1, 
        "id": "b6e0dd784ee2e4a47cfb823b503a695e", 
        "latitude": 45.66422806123289, 
        "longitude": 12.245916344618422, 
        "name": "Borsa", 
        "timestamp": "2017-08-15T04:46:30.358000Z"
      }, 
      {
        "empty_slots": 0, 
        "extra": {
          "description": "Viale Nino Bixio", 
          "status": "online"
        }, 
        "free_bikes": 6, 
        "id": "99cf02d41146c0cc2d7c190faa9f1c10", 
        "latitude": 45.67010961663399, 
        "longitude": 12.250948644778873, 
        "name": "Porta San Tommaso", 
        "timestamp": "2017-08-15T04:46:30.371000Z"
      }, 
      {
        "empty_slots": 3, 
        "extra": {
          "description": "Riviera Garibaldi", 
          "status": "online"
        }, 
        "free_bikes": 4, 
        "id": "f8f5866321a6d2a2d94068d0e8b52e90", 
        "latitude": 45.664214626807, 
        "longitude": 12.249820009856421, 
        "name": "Universita`", 
        "timestamp": "2017-08-15T04:46:30.372000Z"
      }, 
      {
        "empty_slots": 5, 
        "extra": {
          "description": "Via Lanceri di Novara", 
          "status": "online"
        }, 
        "free_bikes": 6, 
        "id": "87e9777f5d665c6dae52fcc4f56e49e7", 
        "latitude": 45.671835866753504, 
        "longitude": 12.237977573016337, 
        "name": "Lanceri di Novara", 
        "timestamp": "2017-08-15T04:46:30.373000Z"
      }, 
      {
        "empty_slots": 5, 
        "extra": {
          "description": "Ospedale S. Camillo Via Ippolito Nievo", 
          "status": "online"
        }, 
        "free_bikes": 2, 
        "id": "bf7950ffcea95027fe543c1573318d05", 
        "latitude": 45.67524681252291, 
        "longitude": 12.250935044496941, 
        "name": "San Camillo", 
        "timestamp": "2017-08-15T04:46:30.373000Z"
      }, 
      {
        "empty_slots": 3, 
        "extra": {
          "description": "Viale Pindaro", 
          "status": "online"
        }, 
        "free_bikes": 1, 
        "id": "0aeb7574f533be8fe1e14a7295ede5af", 
        "latitude": 45.6834636356833, 
        "longitude": 12.21903231111446, 
        "name": "Piscine", 
        "timestamp": "2017-08-15T04:46:30.375000Z"
      }, 
      {
        "empty_slots": 7, 
        "extra": {
          "description": "Via Cal di Breda", 
          "status": "online"
        }, 
        "free_bikes": 4, 
        "id": "fb743fa4b5ff733cc36377e737b1f741", 
        "latitude": 45.69026119487225, 
        "longitude": 12.26627454274444, 
        "name": "Sede Prov. S. Artemio", 
        "timestamp": "2017-08-15T04:46:30.376000Z"
      }, 
      {
        "empty_slots": 0, 
        "extra": {
          "description": "Piazza Vittoria", 
          "status": "offline"
        }, 
        "free_bikes": 0, 
        "id": "02fcd00d352eea9a385e9dc92c66a167", 
        "latitude": 45.663619960349266, 
        "longitude": 12.242902992030736, 
        "name": "Vittoria", 
        "timestamp": "2017-08-15T04:46:30.376000Z"
      }, 
      {
        "empty_slots": 10, 
        "extra": {
          "description": "Piazzetta Monte di Pieta`", 
          "status": "online"
        }, 
        "free_bikes": 0, 
        "id": "f3ba8f9a582194fbf989e5c65ae0d851", 
        "latitude": 45.66596949479225, 
        "longitude": 12.246489412880123, 
        "name": "Monte di Pieta`", 
        "timestamp": "2017-08-15T04:46:30.377000Z"
      }, 
      {
        "empty_slots": 2, 
        "extra": {
          "description": "Piazzale Duca d\u00e2\u0080\u0099Aosta", 
          "status": "online"
        }, 
        "free_bikes": 9, 
        "id": "fb3674428773d935e26fde54686950be", 
        "latitude": 45.660598412337954, 
        "longitude": 12.245324911500575, 
        "name": "Stazione FF.SS. Bis", 
        "timestamp": "2017-08-15T04:46:30.378000Z"
      }, 
      {
        "empty_slots": 1, 
        "extra": {
          "description": "Piazza Matteotti", 
          "status": "online"
        }, 
        "free_bikes": 5, 
        "id": "50fd9a7b2dd9f3debd965b3cf5df5f9d", 
        "latitude": 45.667949296437634, 
        "longitude": 12.250890445368896, 
        "name": "Matteotti", 
        "timestamp": "2017-08-15T04:46:30.379000Z"
      }, 
      {
        "empty_slots": 5, 
        "extra": {
          "description": "Viale Brigata Treviso", 
          "status": "online"
        }, 
        "free_bikes": 2, 
        "id": "2f2332eab9a59bb8999fc5a0080d8abe", 
        "latitude": 45.68264358227231, 
        "longitude": 12.253138402693935, 
        "name": "Santa Maria del Rovere", 
        "timestamp": "2017-08-15T04:46:30.385000Z"
      }, 
      {
        "empty_slots": 8, 
        "extra": {
          "description": "Via B. d\u00e2\u0080\u0099Alviano/ Via C.B. Conte di Cavour", 
          "status": "online"
        }, 
        "free_bikes": 0, 
        "id": "91b30a919cd13aa311176fb6d54f3a07", 
        "latitude": 45.66711443603529, 
        "longitude": 12.235334464518019, 
        "name": "SS 40", 
        "timestamp": "2017-08-15T04:46:30.380000Z"
      }, 
      {
        "empty_slots": 5, 
        "extra": {
          "description": "Via Graziano Appiani", 
          "status": "online"
        }, 
        "free_bikes": 2, 
        "id": "5db4bd5a6945b8bf58d0a6382aab71fb", 
        "latitude": 45.66335845638431, 
        "longitude": 12.231704625656107, 
        "name": "Tribunale", 
        "timestamp": "2017-08-15T04:46:30.382000Z"
      }, 
      {
        "empty_slots": 4, 
        "extra": {
          "description": "Viale Monte Grappa", 
          "status": "online"
        }, 
        "free_bikes": 4, 
        "id": "174402e3b6cfc57a8fe554acf2d25808", 
        "latitude": 45.66663083945229, 
        "longitude": 12.229275354353376, 
        "name": "Cittadella Istituzioni", 
        "timestamp": "2017-08-15T04:46:30.384000Z"
      }
    ]
  }
}